{
  "schemaVersion": 1,
  "id": "totos-carpet-tweaks",
  "version": "${version}",

  "name": "Toto's Carpet Tweaks",
  "description": "Adds a few tweaks to the survival experience",
  "authors": [
    "Totorewa"
  ],
  "contact": {
    "homepage": "https://github.com/totorewa",
    "sources": "https://github.com/totorewa/totos-carpet-tweaks"
  },

  "license": "LGPL-3.0",
  "icon": "assets/totos-carpet-tweaks/icon.png",

  "environment": "*",
  "entrypoints": {
    "main": [
      "totoscarpettweaks.TotoCarpetMod"
    ]
  },
  "mixins": [
    "totos-carpet-tweaks.mixins.json"
  ],

  "depends": {
    "fabricloader": ">=0.11.3",
    "minecraft": "1.19.*",
    "java": ">=17",
    "carpet": "*"
  },
  "suggests": {
  },
  "custom": {
    "modmenu": {
      "parent": "carpet"
    }
  }
}
